ilmoitus/__init__.py
ilmoitus/nakyma.py
ilmoitus/sovellus.py
ilmoitus/uusi.py
ilmoitus/viestit.py
django_celery_ilmoitus-0.4.dist-info/METADATA
django_celery_ilmoitus-0.4.dist-info/WHEEL
django_celery_ilmoitus-0.4.dist-info/entry_points.txt
django_celery_ilmoitus-0.4.dist-info/historia.json
django_celery_ilmoitus-0.4.dist-info/top_level.txt
django_celery_ilmoitus-0.4.dist-info/RECORD
