Metadata-Version: 2.4
Name: django-celery-ilmoitus
Version: 0.4
Summary: Ajax/Websocket-pohjainen Django-ilmoitusnäkymätoteutus
Author-email: Antti Hautaniemi <antti.hautaniemi@me.com>
Project-URL: Repository, https://github.com/an7oine/django-celery-ilmoitus.git
Requires-Python: >=3.8
Requires-Dist: celery
Requires-Dist: Django>=3.2
Provides-Extra: websocket
Requires-Dist: celery-viestikanava; extra == "websocket"
Requires-Dist: django-pistoke; extra == "websocket"
